rtl/mac_unit.sv
`timescale 1ns/1ps

import greenmatrix_pkg::*;

module mac_unit (
    input  logic clk,
    input  logic rst,
    input  logic clear_acc,
    input  logic enable,

    input  data_t a,
    input  data_t b,

    input  acc_t acc_in,
    output acc_t acc_out
);

    always_ff @(posedge clk or posedge rst) begin
        if (rst)
            acc_out <= '0;
        else if (clear_acc)
            acc_out <= '0;
        else if (enable)
            acc_out <= acc_in + (a * b);
    end

endmodule

rtl/pe.sv
`timescale 1ns/1ps

import greenmatrix_pkg::*;

module pe (
    input  logic clk,
    input  logic rst,
    input  logic clear_acc,
    input  logic enable,

    input  data_t a_in,
    input  data_t b_in,

    output data_t a_out,
    output data_t b_out,
    output acc_t  acc_out
);

    wire acc_t acc_feedback;

    // Pass matrix A values toward the right.
    // Pass matrix B values downward.
    always_ff @(posedge clk or posedge rst) begin
        if (rst) begin
            a_out <= '0;
            b_out <= '0;
        end
        else if (enable) begin
            a_out <= a_in;
            b_out <= b_in;
        end
    end

    // Each PE contains one multiply-accumulate unit.
    mac_unit u_mac (
        .clk       (clk),
        .rst       (rst),
        .clear_acc (clear_acc),
        .enable    (enable),
        .a         (a_in),
        .b         (b_in),
        .acc_in    (acc_feedback),
        .acc_out   (acc_feedback)
    );

    assign acc_out = acc_feedback;

endmodule

rtl/systolic_array.sv
`timescale 1ns/1ps

import greenmatrix_pkg::*;

module systolic_array #(
    parameter int N = ARRAY_SIZE
) (
    input logic clk,
    input logic rst,
    input logic clear_acc,
    input logic enable,

    // One A input for each row.
    input data_t a_row_in [0:N-1],

    // One B input for each column.
    input data_t b_col_in [0:N-1],

    // N x N result matrix.
    output acc_t c_out [0:N-1][0:N-1]
);

    // Data traveling horizontally through the array.
    data_t a_pipe [0:N-1][0:N-1];

    // Data traveling vertically through the array.
    data_t b_pipe [0:N-1][0:N-1];

    genvar row;
    genvar col;

    generate
        for (row = 0; row < N; row = row + 1) begin : GEN_ROWS
            for (col = 0; col < N; col = col + 1) begin : GEN_COLS

                data_t pe_a_in;
                data_t pe_b_in;

                // First column receives A from the outside.
                // Remaining columns receive A from the PE on the left.
                if (col == 0) begin : GEN_A_LEFT_EDGE
                    assign pe_a_in = a_row_in[row];
                end
                else begin : GEN_A_INTERNAL
                    assign pe_a_in = a_pipe[row][col-1];
                end

                // First row receives B from the outside.
                // Remaining rows receive B from the PE above.
                if (row == 0) begin : GEN_B_TOP_EDGE
                    assign pe_b_in = b_col_in[col];
                end
                else begin : GEN_B_INTERNAL
                    assign pe_b_in = b_pipe[row-1][col];
                end

                pe u_pe (
                    .clk       (clk),
                    .rst       (rst),
                    .clear_acc (clear_acc),
                    .enable    (enable),

                    .a_in      (pe_a_in),
                    .b_in      (pe_b_in),

                    .a_out     (a_pipe[row][col]),
                    .b_out     (b_pipe[row][col]),
                    .acc_out   (c_out[row][col])
                );

            end
        end
    endgenerate

endmodule

tb/tb_array.sv
`timescale 1ns/1ps

import greenmatrix_pkg::*;

module tb_array;

    localparam int N = 2;

    logic clk;
    logic rst;
    logic clear_acc;
    logic enable;

    data_t a_row_in [0:N-1];
    data_t b_col_in [0:N-1];

    acc_t c_out [0:N-1][0:N-1];

    systolic_array #(
        .N(N)
    ) dut (
        .clk       (clk),
        .rst       (rst),
        .clear_acc (clear_acc),
        .enable    (enable),
        .a_row_in  (a_row_in),
        .b_col_in  (b_col_in),
        .c_out     (c_out)
    );

    initial clk = 0;
    always #5 clk = ~clk;

    task drive_inputs(
        input integer a0,
        input integer a1,
        input integer b0,
        input integer b1
    );
        begin
            @(negedge clk);

            a_row_in[0] = a0;
            a_row_in[1] = a1;

            b_col_in[0] = b0;
            b_col_in[1] = b1;
        end
    endtask

    initial begin
        $dumpfile("sim/parameterized_array_wave.vcd");
        $dumpvars(0, tb_array);

        rst       = 1;
        clear_acc = 0;
        enable    = 0;

        a_row_in[0] = 0;
        a_row_in[1] = 0;

        b_col_in[0] = 0;
        b_col_in[1] = 0;

        #12;
        rst    = 0;
        enable = 1;

        // Matrix A:
        // 1 2
        // 3 4
        //
        // Matrix B:
        // 5 6
        // 7 8

        drive_inputs(1, 0, 5, 0);
        drive_inputs(2, 3, 7, 6);
        drive_inputs(0, 4, 0, 8);
        drive_inputs(0, 0, 0, 0);

        @(posedge clk);
        #1;

        $display("----------------------------------------");
        $display("Parameterized GreenMatrix Result");
        $display("[ %0d  %0d ]", c_out[0][0], c_out[0][1]);
        $display("[ %0d  %0d ]", c_out[1][0], c_out[1][1]);
        $display("----------------------------------------");

        if (c_out[0][0] !== 19)
            $fatal(1, "C00 FAILED: expected 19, received %0d", c_out[0][0]);

        if (c_out[0][1] !== 22)
            $fatal(1, "C01 FAILED: expected 22, received %0d", c_out[0][1]);

        if (c_out[1][0] !== 43)
            $fatal(1, "C10 FAILED: expected 43, received %0d", c_out[1][0]);

        if (c_out[1][1] !== 50)
            $fatal(1, "C11 FAILED: expected 50, received %0d", c_out[1][1]);

        $display("PARAMETERIZED 2x2 ARRAY TEST PASSED");
        $display("----------------------------------------");

        #10;
        $finish;
    end

endmodule

sim/parameterized_array_wave.vcd
$date
	Sun Jul 12 19:04:16 2026
$end
$version
	Icarus Verilog
$end
$timescale
	1ps
$end
$scope module tb_array $end
$var parameter 32 ! N $end
$var reg 1 " clear_acc $end
$var reg 1 # clk $end
$var reg 1 $ enable $end
$var reg 1 % rst $end
$scope module dut $end
$var wire 1 " clear_acc $end
$var wire 1 # clk $end
$var wire 1 $ enable $end
$var wire 1 % rst $end
$var parameter 32 & N $end
$scope begin GEN_ROWS[0] $end
$var parameter 2 ' row $end
$scope begin GEN_COLS[0] $end
$var wire 8 ( pe_b_in [7:0] $end
$var wire 8 ) pe_a_in [7:0] $end
$var parameter 2 * col $end
$scope begin GEN_A_LEFT_EDGE $end
$upscope $end
$scope begin GEN_B_TOP_EDGE $end
$upscope $end
$scope module u_pe $end
$var wire 8 + a_in [7:0] $end
$var wire 32 , acc_out [31:0] $end
$var wire 8 - b_in [7:0] $end
$var wire 1 " clear_acc $end
$var wire 1 # clk $end
$var wire 1 $ enable $end
$var wire 1 % rst $end
$var wire 32 . acc_feedback [31:0] $end
$var reg 8 / a_out [7:0] $end
$var reg 8 0 b_out [7:0] $end
$scope module u_mac $end
$var wire 8 1 a [7:0] $end
$var wire 8 2 b [7:0] $end
$var wire 1 " clear_acc $end
$var wire 1 # clk $end
$var wire 1 $ enable $end
$var wire 1 % rst $end
$var wire 32 3 acc_in [31:0] $end
$var reg 32 4 acc_out [31:0] $end
$upscope $end
$upscope $end
$upscope $end
$scope begin GEN_COLS[1] $end
$var wire 8 5 pe_b_in [7:0] $end
$var wire 8 6 pe_a_in [7:0] $end
$var parameter 2 7 col $end
$scope begin GEN_A_INTERNAL $end
$upscope $end
$scope begin GEN_B_TOP_EDGE $end
$upscope $end
$scope module u_pe $end
$var wire 8 8 a_in [7:0] $end
$var wire 32 9 acc_out [31:0] $end
$var wire 8 : b_in [7:0] $end
$var wire 1 " clear_acc $end
$var wire 1 # clk $end
$var wire 1 $ enable $end
$var wire 1 % rst $end
$var wire 32 ; acc_feedback [31:0] $end
$var reg 8 < a_out [7:0] $end
$var reg 8 = b_out [7:0] $end
$scope module u_mac $end
$var wire 8 > a [7:0] $end
$var wire 8 ? b [7:0] $end
$var wire 1 " clear_acc $end
$var wire 1 # clk $end
$var wire 1 $ enable $end
$var wire 1 % rst $end
$var wire 32 @ acc_in [31:0] $end
$var reg 32 A acc_out [31:0] $end
$upscope $end
$upscope $end
$upscope $end
$upscope $end
$scope begin GEN_ROWS[1] $end
$var parameter 2 B row $end
$scope begin GEN_COLS[0] $end
$var wire 8 C pe_b_in [7:0] $end
$var wire 8 D pe_a_in [7:0] $end
$var parameter 2 E col $end
$scope begin GEN_A_LEFT_EDGE $end
$upscope $end
$scope begin GEN_B_INTERNAL $end
$upscope $end
$scope module u_pe $end
$var wire 8 F a_in [7:0] $end
$var wire 32 G acc_out [31:0] $end
$var wire 8 H b_in [7:0] $end
$var wire 1 " clear_acc $end
$var wire 1 # clk $end
$var wire 1 $ enable $end
$var wire 1 % rst $end
$var wire 32 I acc_feedback [31:0] $end
$var reg 8 J a_out [7:0] $end
$var reg 8 K b_out [7:0] $end
$scope module u_mac $end
$var wire 8 L a [7:0] $end
$var wire 8 M b [7:0] $end
$var wire 1 " clear_acc $end
$var wire 1 # clk $end
$var wire 1 $ enable $end
$var wire 1 % rst $end
$var wire 32 N acc_in [31:0] $end
$var reg 32 O acc_out [31:0] $end
$upscope $end
$upscope $end
$upscope $end
$scope begin GEN_COLS[1] $end
$var wire 8 P pe_b_in [7:0] $end
$var wire 8 Q pe_a_in [7:0] $end
$var parameter 2 R col $end
$scope begin GEN_A_INTERNAL $end
$upscope $end
$scope begin GEN_B_INTERNAL $end
$upscope $end
$scope module u_pe $end
$var wire 8 S a_in [7:0] $end
$var wire 32 T acc_out [31:0] $end
$var wire 8 U b_in [7:0] $end
$var wire 1 " clear_acc $end
$var wire 1 # clk $end
$var wire 1 $ enable $end
$var wire 1 % rst $end
$var wire 32 V acc_feedback [31:0] $end
$var reg 8 W a_out [7:0] $end
$var reg 8 X b_out [7:0] $end
$scope module u_mac $end
$var wire 8 Y a [7:0] $end
$var wire 8 Z b [7:0] $end
$var wire 1 " clear_acc $end
$var wire 1 # clk $end
$var wire 1 $ enable $end
$var wire 1 % rst $end
$var wire 32 [ acc_in [31:0] $end
$var reg 32 \ acc_out [31:0] $end
$upscope $end
$upscope $end
$upscope $end
$upscope $end
$upscope $end
$scope task drive_inputs $end
$var integer 32 ] a0 [31:0] $end
$var integer 32 ^ a1 [31:0] $end
$var integer 32 _ b0 [31:0] $end
$var integer 32 ` b1 [31:0] $end
$upscope $end
$upscope $end
$enddefinitions $end
$comment Show the parameter values. $end
$dumpall
b1 R
b0 E
b1 B
b1 7
b0 *
b0 '
b10 &
b10 !
$end
#0
$dumpvars
bx `
bx _
bx ^
bx ]
b0 \
b0 [
b0 Z
b0 Y
b0 X
b0 W
b0 V
b0 U
b0 T
b0 S
b0 Q
b0 P
b0 O
b0 N
b0 M
b0 L
b0 K
b0 J
b0 I
b0 H
b0 G
b0 F
b0 D
b0 C
b0 A
b0 @
b0 ?
b0 >
b0 =
b0 <
b0 ;
b0 :
b0 9
b0 8
b0 6
b0 5
b0 4
b0 3
b0 2
b0 1
b0 0
b0 /
b0 .
b0 -
b0 ,
b0 +
b0 )
b0 (
1%
0$
0#
0"
$end
#5000
1#
#10000
0#
#12000
b0 `
b101 _
b0 ^
b1 ]
1$
0%
#15000
1#
#20000
b110 `
b111 _
b11 ^
b10 ]
b101 (
b101 -
b101 2
b1 )
b1 +
b1 1
0#
#25000
b101 C
b101 H
b101 M
b101 0
b1 6
b1 8
b1 >
b1 /
b101 ,
b101 .
b101 3
b101 4
1#
#30000
b1000 `
b0 _
b100 ^
b0 ]
b110 5
b110 :
b110 ?
b111 (
b111 -
b111 2
b11 D
b11 F
b11 L
b10 )
b10 +
b10 1
0#
#35000
b10011 ,
b10011 .
b10011 3
b10011 4
b111 C
b111 H
b111 M
b111 0
b10 6
b10 8
b10 >
b10 /
b110 9
b110 ;
b110 @
b110 A
b110 P
b110 U
b110 Z
b110 =
b1 <
b1111 G
b1111 I
b1111 N
b1111 O
b101 K
b11 Q
b11 S
b11 Y
b11 J
1#
#40000
b0 `
b0 ^
b1000 5
b1000 :
b1000 ?
b0 (
b0 -
b0 2
b100 D
b100 F
b100 L
b0 )
b0 +
b0 1
0#
#45000
b110 X
b11 W
b10010 T
b10010 V
b10010 [
b10010 \
b111 K
b100 Q
b100 S
b100 Y
b100 J
b101011 G
b101011 I
b101011 N
b101011 O
b1000 P
b1000 U
b1000 Z
b1000 =
b10 <
b10110 9
b10110 ;
b10110 @
b10110 A
b0 C
b0 H
b0 M
b0 0
b0 6
b0 8
b0 >
b0 /
1#
#50000
b0 5
b0 :
b0 ?
b0 D
b0 F
b0 L
0#
#55000
b0 P
b0 U
b0 Z
b0 =
b0 <
b0 K
b0 Q
b0 S
b0 Y
b0 J
b110010 T
b110010 V
b110010 [
b110010 \
b1000 X
b100 W
1#
#60000
0#
#65000
b0 X
b0 W
1#
