rtl/mac_unit.sv
`timescale 1ns/1ps

import greenmatrix_pkg::*;

module mac_unit (
    input  logic clk,
    input  logic rst,
    input  logic clear_acc,
    input  logic enable,

    input  data_t a,
    input  data_t b,

    input  acc_t acc_in,
    output acc_t acc_out
);

    always_ff @(posedge clk or posedge rst) begin
        if (rst)
            acc_out <= '0;
        else if (clear_acc)
            acc_out <= '0;
        else if (enable)
            acc_out <= acc_in + (a * b);
    end

endmodule

rtl/pe.sv
`timescale 1ns/1ps

import greenmatrix_pkg::*;

module pe (
    input  logic clk,
    input  logic rst,
    input  logic clear_acc,
    input  logic enable,

    input  data_t a_in,
    input  data_t b_in,

    output data_t a_out,
    output data_t b_out,
    output acc_t  acc_out
);

    wire acc_t acc_feedback;

    // Pass matrix A values toward the right.
    // Pass matrix B values downward.
    always_ff @(posedge clk or posedge rst) begin
        if (rst) begin
            a_out <= '0;
            b_out <= '0;
        end
        else if (enable) begin
            a_out <= a_in;
            b_out <= b_in;
        end
    end

    // Each PE contains one multiply-accumulate unit.
    mac_unit u_mac (
        .clk       (clk),
        .rst       (rst),
        .clear_acc (clear_acc),
        .enable    (enable),
        .a         (a_in),
        .b         (b_in),
        .acc_in    (acc_feedback),
        .acc_out   (acc_feedback)
    );

    assign acc_out = acc_feedback;

endmodule

tb/tb_pe.sv
`timescale 1ns/1ps

import greenmatrix_pkg::*;

module tb_pe;

    logic clk;
    logic rst;
    logic clear_acc;
    logic enable;

    data_t a_in;
    data_t b_in;

    data_t a_out;
    data_t b_out;
    acc_t  acc_out;

    pe dut (
        .clk       (clk),
        .rst       (rst),
        .clear_acc (clear_acc),
        .enable    (enable),
        .a_in      (a_in),
        .b_in      (b_in),
        .a_out     (a_out),
        .b_out     (b_out),
        .acc_out   (acc_out)
    );

    // 100 MHz clock
    initial clk = 0;
    always #5 clk = ~clk;

    initial begin
        $dumpfile("sim/pe_wave.vcd");
        $dumpvars(0, tb_pe);

        rst       = 1;
        clear_acc = 0;
        enable    = 0;
        a_in      = 0;
        b_in      = 0;

        // Reset the PE
        #12;
        rst = 0;

        // First MAC operation: 2 x 3 = 6
        @(negedge clk);
        enable = 1;
        a_in   = 2;
        b_in   = 3;

        @(posedge clk);
        #1;
        if (acc_out !== 6)
            $fatal(1, "TEST 1 FAILED: expected 6, received %0d", acc_out);
        else
            $display("TEST 1 PASSED: 2 x 3 = %0d", acc_out);

        if ((a_out !== 2) || (b_out !== 3))
            $fatal(1, "DATA PASS FAILED: a_out=%0d b_out=%0d", a_out, b_out);
        else
            $display("DATA PASS PASSED: a_out=%0d b_out=%0d", a_out, b_out);

        // Second MAC operation: 6 + (4 x 5) = 26
        @(negedge clk);
        a_in = 4;
        b_in = 5;

        @(posedge clk);
        #1;
        if (acc_out !== 26)
            $fatal(1, "TEST 2 FAILED: expected 26, received %0d", acc_out);
        else
            $display("TEST 2 PASSED: 6 + (4 x 5) = %0d", acc_out);

        // Disable should hold the accumulator and outputs
        @(negedge clk);
        enable = 0;
        a_in   = 7;
        b_in   = 7;

        @(posedge clk);
        #1;
        if (acc_out !== 26)
            $fatal(1, "ENABLE TEST FAILED: expected 26, received %0d", acc_out);
        else
            $display("ENABLE TEST PASSED: accumulator held at %0d", acc_out);

        // Clear the accumulator
        @(negedge clk);
        clear_acc = 1;

        @(posedge clk);
        #1;
        if (acc_out !== 0)
            $fatal(1, "CLEAR TEST FAILED: expected 0, received %0d", acc_out);
        else
            $display("CLEAR TEST PASSED: accumulator reset to %0d", acc_out);

        clear_acc = 0;

        $display("----------------------------------------");
        $display("ALL PROCESSING ELEMENT TESTS PASSED");
        $display("----------------------------------------");

        #10;
        $finish;
    end

endmodule

sim/pe_wave.vcd
$date
	Sun Jul 12 18:52:51 2026
$end
$version
	Icarus Verilog
$end
$timescale
	1ps
$end
$scope module tb_pe $end
$var wire 8 ! b_out [7:0] $end
$var wire 32 " acc_out [31:0] $end
$var wire 8 # a_out [7:0] $end
$var reg 8 $ a_in [7:0] $end
$var reg 8 % b_in [7:0] $end
$var reg 1 & clear_acc $end
$var reg 1 ' clk $end
$var reg 1 ( enable $end
$var reg 1 ) rst $end
$scope module dut $end
$var wire 8 * a_in [7:0] $end
$var wire 32 + acc_out [31:0] $end
$var wire 8 , b_in [7:0] $end
$var wire 1 & clear_acc $end
$var wire 1 ' clk $end
$var wire 1 ( enable $end
$var wire 1 ) rst $end
$var wire 32 - acc_feedback [31:0] $end
$var reg 8 . a_out [7:0] $end
$var reg 8 / b_out [7:0] $end
$scope module u_mac $end
$var wire 8 0 a [7:0] $end
$var wire 8 1 b [7:0] $end
$var wire 1 & clear_acc $end
$var wire 1 ' clk $end
$var wire 1 ( enable $end
$var wire 1 ) rst $end
$var wire 32 2 acc_in [31:0] $end
$var reg 32 3 acc_out [31:0] $end
$upscope $end
$upscope $end
$upscope $end
$enddefinitions $end
$comment Show the parameter values. $end
$dumpall
$end
#0
$dumpvars
b0 3
b0 2
b0 1
b0 0
b0 /
b0 .
b0 -
b0 ,
b0 +
b0 *
1)
0(
0'
0&
b0 %
b0 $
b0 #
b0 "
b0 !
$end
#5000
1'
#10000
0'
#12000
0)
#15000
1'
#20000
b11 %
b11 ,
b11 1
b10 $
b10 *
b10 0
1(
0'
#25000
b11 !
b11 /
b10 #
b10 .
b110 "
b110 +
b110 -
b110 2
b110 3
1'
#30000
b101 %
b101 ,
b101 1
b100 $
b100 *
b100 0
0'
#35000
b11010 "
b11010 +
b11010 -
b11010 2
b11010 3
b101 !
b101 /
b100 #
b100 .
1'
#40000
b111 %
b111 ,
b111 1
b111 $
b111 *
b111 0
0(
0'
#45000
1'
#50000
1&
0'
#55000
b0 "
b0 +
b0 -
b0 2
b0 3
1'
#56000
0&
